pyflwdir/__init__.py
pyflwdir/arithmetics.py
pyflwdir/basins.py
pyflwdir/core.py
pyflwdir/core_conversion.py
pyflwdir/core_d8.py
pyflwdir/core_ldd.py
pyflwdir/core_nextxy.py
pyflwdir/dem.py
pyflwdir/flwdir.py
pyflwdir/gis_utils.py
pyflwdir/pyflwdir.py
pyflwdir/regions.py
pyflwdir/rivers.py
pyflwdir/streams.py
pyflwdir/subgrid.py
pyflwdir/upscale.py
pyflwdir-0.5.10.dist-info/LICENSE
pyflwdir-0.5.10.dist-info/WHEEL
pyflwdir-0.5.10.dist-info/METADATA
pyflwdir-0.5.10.dist-info/RECORD
