Metadata-Version: 2.3
Name: pyflwdir
Version: 0.5.10
Summary: Fast methods to work with hydro- and topography data in pure Python.
Author-email: Dirk Eilander <dirk.eilander@deltares.nl>
Requires-Python: >=3.9
Classifier: License :: OSI Approved :: MIT License
Requires-Dist: affine
Requires-Dist: numba>=0.54,<1.0
Requires-Dist: numpy
Requires-Dist: scipy
Requires-Dist: nbsphinx ; extra == "doc"
Requires-Dist: pydata-sphinx-theme ; extra == "doc"
Requires-Dist: sphinx ; extra == "doc"
Requires-Dist: sphinx_design ; extra == "doc"
Requires-Dist: cartopy>=0.20 ; extra == "examples"
Requires-Dist: descartes ; extra == "examples"
Requires-Dist: geopandas>0.8 ; extra == "examples"
Requires-Dist: jupyter ; extra == "examples"
Requires-Dist: matplotlib ; extra == "examples"
Requires-Dist: rasterio ; extra == "examples"
Requires-Dist: pandoc ; extra == "examples"
Requires-Dist: pyflwdir[test, doc, examples] ; extra == "full"
Requires-Dist: black[jupyter] ; extra == "test"
Requires-Dist: pre-commit ; extra == "test"
Requires-Dist: pytest>=2.7.3 ; extra == "test"
Requires-Dist: pytest-cov ; extra == "test"
Project-URL: Documentation, https://deltares.github.io/pyflwdir
Project-URL: Home, https://github.com/Deltares/pyflwdir
Provides-Extra: doc
Provides-Extra: examples
Provides-Extra: full
Provides-Extra: test
